MANIFEST.in
setup.py
communitweet/Demographics.py
communitweet/ForceAtlas2.py
communitweet/GraphFactory.py
communitweet/Hydration.py
communitweet/Processing.py
communitweet/Slicing.py
communitweet/Summarize.py
communitweet/Unshortening.py
communitweet/__init__.py
communitweet/fa2util.py
communitweet.egg-info/PKG-INFO
communitweet.egg-info/SOURCES.txt
communitweet.egg-info/dependency_links.txt
communitweet.egg-info/not-zip-safe
communitweet.egg-info/requires.txt
communitweet.egg-info/top_level.txt
communitweet/data_sheets/population_data.csv
communitweet/data_sheets/poverty_data.csv
communitweet/data_sheets/race_data.csv