Metadata-Version: 1.0
Name: communitweet
Version: 1.3
Summary: A package that wraps tools for harvesting, hydrating, cleaning and visualize twitter data
Home-page: https://github.com/HolzmanoLagrene/FacharbeitLenzBaumannHS16FS17
Author: Lenz Baumann
Author-email: lnzbmnn@gmail.com
License: MIT
Platform: UNKNOWN
